stonefish_license_manager/__init__.py
stonefish_license_manager/stonefish-license-manager.cpython-311.sfc
stonefish_license_manager-0.5.42.dist-info/METADATA
stonefish_license_manager-0.5.42.dist-info/RECORD
stonefish_license_manager-0.5.42.dist-info/WHEEL
stonefish_license_manager-0.5.42.dist-info/entry_points.txt
stonefish_license_manager-0.5.42.dist-info/licenses/LICENSE
stonefish_license_manager-0.5.42.dist-info/top_level.txt
stonefish_license_manager-0.5.42.dist-info/RECORD