Metadata-Version: 2.4
Name: stonefish-license-manager
Version: 0.5.42
Summary: Stonefish license manager for Python
Author-email: Nico Schlömer <nico.schloemer@gmail.com>
License-Expression: LicenseRef-Proprietary
Project-URL: Homepage, https://github.com/stonefish-dev/license-manager
Project-URL: Issues, https://github.com/stonefish-dev/license-manager/issues
Classifier: Development Status :: 5 - Production/Stable
Classifier: Operating System :: OS Independent
Classifier: Programming Language :: Python
Classifier: Programming Language :: Python :: 3 :: Only
Classifier: Programming Language :: Python :: 3.10
Classifier: Programming Language :: Python :: 3.11
Classifier: Programming Language :: Python :: 3.12
Classifier: Programming Language :: Python :: 3.13
Classifier: Programming Language :: Python :: 3.14
Classifier: Topic :: Utilities
Requires-Python: >=3.10
License-File: LICENSE
Requires-Dist: cryptography>=3.1
Requires-Dist: getmac
Requires-Dist: platformdirs>=3.2
Requires-Dist: py-machineid
Requires-Dist: python-package-info
Requires-Dist: requests
Requires-Dist: requests-cache>=1.2
Requires-Dist: rich
Requires-Dist: rich-argparse
Dynamic: license-file
Requires-Dist: stonefish_runtime>=0.3.5
